GetCCWarc/GetCCWarc.py
GetCCWarc/__init__.py
GetCCWarc/_version.py
GetCCWarc-0.0.1.dev34.dist-info/AUTHORS
GetCCWarc-0.0.1.dev34.dist-info/LICENSE
GetCCWarc-0.0.1.dev34.dist-info/METADATA
GetCCWarc-0.0.1.dev34.dist-info/WHEEL
GetCCWarc-0.0.1.dev34.dist-info/entry_points.txt
GetCCWarc-0.0.1.dev34.dist-info/pbr.json
GetCCWarc-0.0.1.dev34.dist-info/top_level.txt
GetCCWarc-0.0.1.dev34.dist-info/RECORD
